CPET/__init__.py
CPET/utils/math_module.cpython-311-x86_64-linux-gnu.so
CPET/utils/math_module.c
CPET/utils/transformations.py
CPET/utils/c_ops.py
CPET/utils/io.py
CPET/utils/parallel.py
CPET/utils/fields.py
CPET/utils/fastmath.py
CPET/utils/visualize.py
CPET/utils/gpu.py
CPET/utils/calculator.py
CPET/source/benchmark.py
CPET/source/CPET.py
CPET/source/__init__.py
CPET/source/cluster.py
CPET/source/pca.py
CPET/source/calculator.py
CPET/source/scripts/cpet.py
CPET/source/scripts/benchmark_sample_step.py
CPET/source/scripts/tensor_based_cluster_double.py
CPET/source/scripts/residue_breakdown_analysis.py
CPET/source/scripts/electrostatic_interaction_QM.py
CPET/source/scripts/benchmark_radius_convergence.py
pycpet-0.0.7.dist-info/top_level.txt
pycpet-0.0.7.dist-info/RECORD
pycpet-0.0.7.dist-info/METADATA
pycpet-0.0.7.dist-info/entry_points.txt
pycpet-0.0.7.dist-info/WHEEL
pycpet-0.0.7.dist-info/licenses/LICENSE
