Metadata-Version: 2.4
Name: pycpet
Version: 0.0.7
Summary: Computing Electric Field Topologies and Other Features in High-Throughput
Author-email: Pujan Ajmera <ajmerapujan@gmail.com>
License-Expression: MIT
Project-URL: Homepage, https://github.com/pujanajmera/pycpet
Project-URL: Issues, https://github.com/pujanajmera/pycpet/issues
Classifier: Programming Language :: Python :: 3
Classifier: Operating System :: OS Independent
Requires-Python: >=3.9
License-File: LICENSE
Requires-Dist: torch
Requires-Dist: numba
Requires-Dist: numpy<2
Requires-Dist: pandas
Requires-Dist: scikit-learn
Requires-Dist: kneed
Requires-Dist: tensorly
Requires-Dist: matplotlib
Requires-Dist: tqdm
Requires-Dist: seaborn
Requires-Dist: scikit-learn-extra
Requires-Dist: psutil
Dynamic: license-file
